setup.cfg
setup.py
papersizes/__init__.py
papersizes/papersize.py
papersizes/papersizes.py
papersizes/parse.py
papersizes/ratios.py
papersizes/units.py
papersizes.egg-info/PKG-INFO
papersizes.egg-info/SOURCES.txt
papersizes.egg-info/dependency_links.txt
papersizes.egg-info/not-zip-safe
papersizes.egg-info/top_level.txt