Metadata-Version: 1.1
Name: papersizes
Version: 0.6.1
Summary: Paper sizes and manipulations
Home-page: http://github.com/idmillington/papersizes
Author: Ian Millington
Author-email: idmillington@googlemail.com
License: UNKNOWN
Download-URL: https://github.com/idmillington/papersizes/tarball/master
Keywords: pdf,papersizes,print,design
Platform: UNKNOWN
Classifier: Programming Language :: Python :: 3
Classifier: Development Status :: 4 - Beta
Classifier: Environment :: Console
Classifier: Intended Audience :: Developers
Classifier: License :: OSI Approved :: MIT License
Classifier: Operating System :: OS Independent
Classifier: Topic :: Multimedia :: Graphics
